curies_processing/.DS_Store
curies_processing/__init__.py
curies_processing/api.py
curies_processing/py.typed
curies_processing/resources/.DS_Store
curies_processing/resources/__init__.py
curies_processing/resources/goc.py
curies_processing/resources/goc.tsv
curies_processing/rules.json
curies_processing/version.py
curies_processing-0.1.5.dist-info/licenses/LICENSE
curies_processing-0.1.5.dist-info/WHEEL
curies_processing-0.1.5.dist-info/METADATA
curies_processing-0.1.5.dist-info/RECORD
